kotti2/__init__.py
kotti2/events.py
kotti2/fanstatic.py
kotti2/filedepot.py
kotti2/interfaces.py
kotti2/message.py
kotti2/migrate.py
kotti2/populate.py
kotti2/request.py
kotti2/resources.py
kotti2/sanitizers.py
kotti2/security.py
kotti2/sqla.py
kotti2/testing.py
kotti2/traversal.py
kotti2/url_normalizer.py
kotti2/util.py
kotti2/workflow.py
kotti2/workflow.zcml
kotti2/alembic/env.py
kotti2/alembic/script.py.mako
kotti2/alembic/versions/1063d7178fa_add_node_path_column.py
kotti2/alembic/versions/37a05f6246af_enlarge_name_title_path.py
kotti2/alembic/versions/413fa5fcc581_add_filedepot.py
kotti2/alembic/versions/4a3de0d0804a_add_foreignkey_indices.py
kotti2/alembic/versions/559ce6eb0949_update_node_path_column.py
kotti2/alembic/versions/57fecf5dbd62_initialize_workflow.py
kotti2/alembic/versions/814c4ec72f1_add_file_columns_to_images_table.py
kotti2/alembic/versions/9398ccf41c2_add_content_state_fo.py
kotti2/locale/Kotti.pot
kotti2/locale/cs/LC_MESSAGES/Kotti.mo
kotti2/locale/cs/LC_MESSAGES/Kotti.po
kotti2/locale/de/LC_MESSAGES/Kotti.mo
kotti2/locale/de/LC_MESSAGES/Kotti.po
kotti2/locale/en/LC_MESSAGES/Kotti.mo
kotti2/locale/en/LC_MESSAGES/Kotti.po
kotti2/locale/fr_FR/LC_MESSAGES/Kotti.mo
kotti2/locale/fr_FR/LC_MESSAGES/Kotti.po
kotti2/locale/it/LC_MESSAGES/Kotti.mo
kotti2/locale/it/LC_MESSAGES/Kotti.po
kotti2/locale/ja/LC_MESSAGES/Kotti.mo
kotti2/locale/ja/LC_MESSAGES/Kotti.po
kotti2/locale/ko/LC_MESSAGES/Kotti.mo
kotti2/locale/ko/LC_MESSAGES/Kotti.po
kotti2/locale/nl/LC_MESSAGES/Kotti.mo
kotti2/locale/nl/LC_MESSAGES/Kotti.po
kotti2/locale/pl/LC_MESSAGES/Kotti.mo
kotti2/locale/pl/LC_MESSAGES/Kotti.po
kotti2/locale/pt/LC_MESSAGES/Kotti.mo
kotti2/locale/pt/LC_MESSAGES/Kotti.po
kotti2/locale/sv/LC_MESSAGES/Kotti.mo
kotti2/locale/sv/LC_MESSAGES/Kotti.po
kotti2/static/base.css
kotti2/static/base.min.css
kotti2/static/contents.js
kotti2/static/contents.min.js
kotti2/static/edit.css
kotti2/static/edit.min.css
kotti2/static/favicon.ico
kotti2/static/icon-transparent.png
kotti2-0.1.2.dist-info/licenses/AUTHORS.txt
kotti2-0.1.2.dist-info/licenses/LICENSE
kotti2-0.1.2.dist-info/licenses/LICENSE.txt
kotti2-0.1.2.dist-info/METADATA
kotti2-0.1.2.dist-info/WHEEL
kotti2-0.1.2.dist-info/entry_points.txt
kotti2-0.1.2.dist-info/top_level.txt
kotti2-0.1.2.dist-info/RECORD
