Metadata-Version: 2.4
Name: kotti2
Version: 0.1.2
Summary: Kotti2: A fork/variant of Kotti CMS
Home-page: http://kotti2.pylonsproject.org/
Author: Kotti2 Developers
Author-email: Your Name <your@email.com>
License: MIT
Requires-Python: >=3.7
License-File: LICENSE
License-File: LICENSE.txt
License-File: AUTHORS.txt
Dynamic: author
Dynamic: home-page
Dynamic: license-file
